yabra/__init__.py
yabra/doc/__init__.py
yabra/doc/__main__.py
yabra/doc/base_doc.py
yabra/doc/cnpj.py
yabra/doc/cpf.py
yabra/doc/exc.py
yabra/doc/generate_doc.py
yabra/doc/types.py
yabra/py.typed
yabra-0.1.0.dist-info/WHEEL
yabra-0.1.0.dist-info/METADATA
yabra-0.1.0.dist-info/RECORD
