Metadata-Version: 2.3
Name: yabra
Version: 0.1.0
Summary: Yet Another Brazilian library
Author: Leandro de Souza
Author-email: Leandro de Souza <leandrodesouzadev@gmail.com>
Requires-Dist: click>=8.3.1 ; extra == 'cli'
Requires-Python: >=3.12
Provides-Extra: cli
